cryptoadvance/spectrum/__init__.py
cryptoadvance/spectrum/__main__.py
cryptoadvance/spectrum/_version.py
cryptoadvance/spectrum/config.py
cryptoadvance/spectrum/db.py
cryptoadvance/spectrum/elsock.py
cryptoadvance/spectrum/server.py
cryptoadvance/spectrum/spectrum.py
cryptoadvance/spectrum/spectrum_error.py
cryptoadvance/spectrum/util.py
cryptoadvance/spectrum/util_specter.py
cryptoadvance/spectrum/cli/__init__.py
cryptoadvance/spectrum/cli/cli_server.py
cryptoadvance/spectrum/server_endpoints/__init__.py
cryptoadvance/spectrum/server_endpoints/core_api.py
cryptoadvance/spectrum/server_endpoints/healthz.py
cryptoadvance.spectrum-0.6.9.dist-info/LICENSE
cryptoadvance.spectrum-0.6.9.dist-info/METADATA
cryptoadvance.spectrum-0.6.9.dist-info/WHEEL
cryptoadvance.spectrum-0.6.9.dist-info/top_level.txt
cryptoadvance.spectrum-0.6.9.dist-info/RECORD
