Metadata-Version: 2.1
Name: cryptoadvance.spectrum
Version: 0.6.9
Summary: Implements A Bitcoin Core API which querying an Electrum
Author: Stepan Snigirev, k9ert
License: MIT License
Project-URL: Homepage, https://github.com/cryptoadvance/spectrum
Classifier: Programming Language :: Python :: 3
Classifier: License :: OSI Approved :: MIT License
Classifier: Operating System :: OS Independent
Classifier: Framework :: Flask
Requires-Python: >=3.10
License-File: LICENSE
Requires-Dist: embit >=0.6.1
Requires-Dist: Flask >=2.1.1
Requires-Dist: Flask-SQLAlchemy ==2.5.1
Requires-Dist: sqlalchemy ==2.0.30
Requires-Dist: psycopg2-binary
Requires-Dist: requests >=2.26.0
Requires-Dist: pysocks ==1.7.1
Provides-Extra: test
Requires-Dist: pytest >=7.1.3 ; extra == 'test'
Requires-Dist: pytest-cov[all] ; extra == 'test'
Requires-Dist: mock ; extra == 'test'
Requires-Dist: black ; extra == 'test'
Requires-Dist: pre-commit ; extra == 'test'
Requires-Dist: bdkpython ; extra == 'test'
